img_focus/__init__.py
img_focus/detector.py
img_focus/models/vit_s_focus.onnx
img_focus-0.1.1.dist-info/METADATA
img_focus-0.1.1.dist-info/WHEEL
img_focus-0.1.1.dist-info/top_level.txt
img_focus-0.1.1.dist-info/RECORD
