Metadata-Version: 2.4
Name: img-focus
Version: 0.1.1
Summary: Find image regions of interest with an ONNX ViT.
Author-email: Goueffon Jules <jules.goueffon89@gmail.com>
License: MIT
Project-URL: Homepage, https://github.com/julesGoueffon/jgo_saliency
Project-URL: Bug Tracker, https://github.com/julesGoueffon/jgo_saliency/issues
Classifier: Programming Language :: Python :: 3
Classifier: License :: OSI Approved :: MIT License
Classifier: Operating System :: OS Independent
Classifier: Topic :: Scientific/Engineering :: Image Processing
Classifier: Intended Audience :: Developers
Classifier: Intended Audience :: Science/Research
Requires-Python: >=3.8
Requires-Dist: numpy
Requires-Dist: opencv-python-headless
Requires-Dist: Pillow
Requires-Dist: onnxruntime
Requires-Dist: albumentations
Requires-Dist: importlib-resources
